scanless/__init__.py
scanless/scanless.py
scanless/scanners/__init__.py
scanless/scanners/hackertarget.py
scanless/scanners/ipfingerprints.py
scanless/scanners/pingeu.py
scanless/scanners/portcheckers.py
scanless/scanners/spiderip.py
scanless/scanners/standingtech.py
scanless/scanners/t1shopper.py
scanless/scanners/viewdns.py
scanless/scanners/yougetsignal.py
scanless-1.0.10.dist-info/METADATA
scanless-1.0.10.dist-info/WHEEL
scanless-1.0.10.dist-info/entry_points.txt
scanless-1.0.10.dist-info/top_level.txt
scanless-1.0.10.dist-info/RECORD
