Metadata-Version: 2.1
Name: scanless
Version: 1.0.10
Summary: An online port scan scraper.
Home-page: https://github.com/vesche/scanless
Author: Austin Jackson
Author-email: vesche@protonmail.com
License: Unlicense
Platform: UNKNOWN
Classifier: Development Status :: 5 - Production/Stable
Classifier: Environment :: Console
Classifier: Intended Audience :: Information Technology
Classifier: License :: OSI Approved :: MIT License
Classifier: Programming Language :: Python :: 2
Classifier: Programming Language :: Python :: 2.7
Classifier: Programming Language :: Python :: 3
Classifier: Programming Language :: Python :: 3.6
Classifier: Topic :: Security
Requires-Dist: beautifulsoup4
Requires-Dist: requests
